voip_shifts/__init__.py
voip_shifts/bot.py
voip_shifts/config.py
voip_shifts/models.py
voip_shifts/shift_class.py
voip_shifts-0.4.4.dist-info/METADATA
voip_shifts-0.4.4.dist-info/WHEEL
voip_shifts-0.4.4.dist-info/top_level.txt
voip_shifts-0.4.4.dist-info/RECORD
