Metadata-Version: 2.1
Name: voip-shifts
Version: 0.4.4
Summary: Shared modules for voip project
Requires-Dist: redis
Requires-Dist: rq
Requires-Dist: sqlalchemy
Requires-Dist: psycopg2
Requires-Dist: requests
Requires-Dist: telnyx
